flightradar24/__init__.py
flightradar24/core.py
flightradar24/helpers.py
flightradar24-0.3.1.dist-info/LICENSE
flightradar24-0.3.1.dist-info/METADATA
flightradar24-0.3.1.dist-info/WHEEL
flightradar24-0.3.1.dist-info/top_level.txt
flightradar24-0.3.1.dist-info/RECORD
