Metadata-Version: 2.1
Name: flightradar24
Version: 0.3.1
Summary: Data library for Flight Radar 24
Home-page: https://github.com/mkorkmaz/flightradar24
Author: Mehmet Korkmaz
Author-email: mehmet@mkorkmaz.com
License: MIT
Platform: UNKNOWN
